tester/__init__.py
tester/cli_parser.py
tester/common_errors.py
tester/exam_test_case.py
tester/exam_test_case_exam.py
tester/exam_test_result.py
tester/exam_test_result_exam.py
tester/exceptions.py
tester/fail_message.py
tester/helper_functions.py
tester/run_tests.py
tester/sentry.py
python_tester-3.1.2.dist-info/METADATA
python_tester-3.1.2.dist-info/WHEEL
python_tester-3.1.2.dist-info/entry_points.txt
python_tester-3.1.2.dist-info/licenses/LICENSE
python_tester-3.1.2.dist-info/RECORD
