Metadata-Version: 2.4
Name: python-tester
Version: 3.1.2
Summary: Add your description here
Project-URL: Repository, https://github.com/AndreasArne/python-examination.git
Author-email: Andreas Arnesson <aar@bth.se>
License-File: LICENSE
Requires-Python: >=3.10
Requires-Dist: colorama>=0.4.6
Requires-Dist: pylint>=3.3.7
